alpaca_cli/__init__.py
alpaca_cli/cli/__init_.py
alpaca_cli/cli/decorators.py
alpaca_cli/cli/groups/config.py
alpaca_cli/cli/groups/dashboard.py
alpaca_cli/cli/groups/data/__init__.py
alpaca_cli/cli/groups/data/corporate_actions.py
alpaca_cli/cli/groups/data/crypto.py
alpaca_cli/cli/groups/data/news.py
alpaca_cli/cli/groups/data/options.py
alpaca_cli/cli/groups/data/screeners.py
alpaca_cli/cli/groups/data/stock.py
alpaca_cli/cli/groups/trading/__init__.py
alpaca_cli/cli/groups/trading/account.py
alpaca_cli/cli/groups/trading/assets.py
alpaca_cli/cli/groups/trading/contracts.py
alpaca_cli/cli/groups/trading/corporate_actions.py
alpaca_cli/cli/groups/trading/market_info.py
alpaca_cli/cli/groups/trading/orders.py
alpaca_cli/cli/groups/trading/positions.py
alpaca_cli/cli/groups/trading/stream.py
alpaca_cli/cli/groups/trading/watchlists.py
alpaca_cli/cli/main.py
alpaca_cli/cli/theme.py
alpaca_cli/cli/utils.py
alpaca_cli/core/client.py
alpaca_cli/core/config.py
alpaca_cli/core/constants.py
alpaca_cli/logger/__init__.py
alpaca_cli/logger/logger.py
alpaca_cli/py.typed
alpaca_cli-0.3.0.dist-info/WHEEL
alpaca_cli-0.3.0.dist-info/entry_points.txt
alpaca_cli-0.3.0.dist-info/METADATA
alpaca_cli-0.3.0.dist-info/RECORD
