Metadata-Version: 2.3
Name: alpaca-cli
Version: 0.3.0
Summary: Add your description here
Author: hades
Author-email: hades <nischalbhattaraipi@gmail.com>
Requires-Dist: alpaca-py>=0.43.2
Requires-Dist: click>=8.3.1
Requires-Dist: rich>=14.2.0
Requires-Dist: rich-click>=1.8.3
Requires-Python: >=3.14
